{
  "slider": [
    {
      "symbol": "^BVSP",
      "price": 188258.9,
      "change": 0.05,
      "changeStr": "\u002B0.05%"
    },
    {
      "symbol": "PETR4",
      "price": 48.51,
      "change": -0.88,
      "changeStr": "-0.88%"
    },
    {
      "symbol": "VALE3",
      "price": 83.69,
      "change": 0.72,
      "changeStr": "\u002B0.72%"
    },
    {
      "symbol": "ITUB4",
      "price": 43.46,
      "change": -0.07,
      "changeStr": "-0.07%"
    },
    {
      "symbol": "BBDC4",
      "price": 19.21,
      "change": 0.66,
      "changeStr": "\u002B0.66%"
    },
    {
      "symbol": "BBAS3",
      "price": 23.44,
      "change": 0.04,
      "changeStr": "\u002B0.04%"
    },
    {
      "symbol": "MGLU3",
      "price": 8.78,
      "change": -0.45,
      "changeStr": "-0.45%"
    },
    {
      "symbol": "ABEV3",
      "price": 15.48,
      "change": 0.19,
      "changeStr": "\u002B0.19%"
    },
    {
      "symbol": "WEGE3",
      "price": 50.65,
      "change": 0.06,
      "changeStr": "\u002B0.06%"
    }
  ],
  "news": [
    {
      "title": "Petr\u00F3leo despenca nesta quarta e vai abaixo de US$100 ap\u00F3s Trump anunciar cessar-fogo de duas semanas",
      "source": "G1 Economia",
      "url": "https://g1.globo.com/economia/noticia/2026/04/08/petroleo-despenca-nesta-quarta-e-vai-abaixo-de-us100-apos-trump-anunciar-cessar-fogo-de-duas-semanas.ghtml",
      "date": "Wed, 08 Apr 2026 10:28:56 -0000"
    },
    {
      "title": "China reage \u00E0 inclus\u00E3o da montadora de carros el\u00E9tricos BYD em \u0027lista suja\u0027 do trabalho escravo",
      "source": "G1 Economia",
      "url": "https://g1.globo.com/trabalho-e-carreira/noticia/2026/04/08/china-reage-a-inclusao-da-montadora-de-carros-eletricos-byd-em-lista-suja-do-trabalho-escravo.ghtml",
      "date": "Wed, 08 Apr 2026 09:49:07 -0000"
    },
    {
      "title": "A\u00E7\u00F5es europeias sobem com a onda de al\u00EDvio ap\u00F3s o cessar-fogo no Oriente M\u00E9dio",
      "source": "G1 Economia",
      "url": "https://g1.globo.com/economia/noticia/2026/04/08/acoes-europeias-sobem-com-a-apos-o-cessar-fogo-no-oriente-medio.ghtml",
      "date": "Wed, 08 Apr 2026 08:07:44 -0000"
    },
    {
      "title": "ASAP, brainstorming, mindset: entenda os principais termos do \u2018corporativ\u00EAs\u2019",
      "source": "G1 Economia",
      "url": "https://g1.globo.com/trabalho-e-carreira/noticia/2026/04/08/asap-brainstorming-mindset-entenda-os-principais-termos-do-corporatives.ghtml",
      "date": "Wed, 08 Apr 2026 07:01:35 -0000"
    },
    {
      "title": "Cria\u00E7\u00E3o de pacas para produ\u00E7\u00E3o de carne exige autoriza\u00E7\u00E3o ambiental; investimento pode chegar a R$ 400 mil",
      "source": "G1 Economia",
      "url": "https://g1.globo.com/economia/agronegocios/globo-rural/noticia/2026/04/08/criacao-de-pacas-para-producao-de-carne-exige-autorizacao-ambiental.ghtml",
      "date": "Wed, 08 Apr 2026 06:00:59 -0000"
    },
    {
      "title": "\u0027\u00C9 guerra, n\u00E3o gan\u00E2ncia\u0027: o que amea\u00E7a o pacote de Lula para segurar o pre\u00E7o do diesel",
      "source": "G1 Economia",
      "url": "https://g1.globo.com/economia/noticia/2026/04/08/o-que-ameaca-o-pacote-de-lula-para-segurar-o-preco-do-diesel.ghtml",
      "date": "Wed, 08 Apr 2026 06:00:37 -0000"
    },
    {
      "title": "Governo adia novamente exig\u00EAncia de biometria para benef\u00EDcios sociais; veja novos prazos",
      "source": "G1 Economia",
      "url": "https://g1.globo.com/economia/noticia/2026/04/08/governo-adia-novamente-exigencia-de-biometria-para-beneficios-sociais-veja-novos-prazos.ghtml",
      "date": "Wed, 08 Apr 2026 05:00:54 -0000"
    },
    {
      "title": "Bolsas asi\u00E1ticas saltam ap\u00F3s queda nos pre\u00E7os do petr\u00F3leo em resposta ao cessar-fogo no Ir\u00E3",
      "source": "G1 Economia",
      "url": "https://g1.globo.com/economia/noticia/2026/04/08/bolsas-asiaticas-saltam-apos-queda-nos-precos-do-petroleo-em-resposta-ao-cessar-fogo-no-ira.ghtml",
      "date": "Wed, 08 Apr 2026 04:56:24 -0000"
    },
    {
      "title": "Governo publica MP com medidas para tentar frear alta nos pre\u00E7os de combust\u00EDveis",
      "source": "G1 Economia",
      "url": "https://g1.globo.com/economia/noticia/2026/04/08/governo-publica-mp-com-medidas-para-tentar-frear-alta-nos-precos-de-combustiveis.ghtml",
      "date": "Wed, 08 Apr 2026 03:20:52 -0000"
    },
    {
      "title": "D\u00F3lar fraco ou real forte? Entenda por que a moeda americana est\u00E1 caindo no ano",
      "source": "G1 Economia",
      "url": "https://g1.globo.com/g1-explica/noticia/2026/04/08/dolar-fraco-ou-real-forte-entenda-por-que-a-moeda-americana-esta-caindo-no-ano.ghtml",
      "date": "Wed, 08 Apr 2026 03:01:11 -0000"
    }
  ]
}